accelbyte_py_sdk/api/eventlog/__init__.py
accelbyte_py_sdk/api/eventlog/models/__init__.py
accelbyte_py_sdk/api/eventlog/models/models_agent_type.py
accelbyte_py_sdk/api/eventlog/models/models_event.py
accelbyte_py_sdk/api/eventlog/models/models_event_id.py
accelbyte_py_sdk/api/eventlog/models/models_event_level.py
accelbyte_py_sdk/api/eventlog/models/models_event_registry.py
accelbyte_py_sdk/api/eventlog/models/models_event_response.py
accelbyte_py_sdk/api/eventlog/models/models_event_response_v2.py
accelbyte_py_sdk/api/eventlog/models/models_event_type.py
accelbyte_py_sdk/api/eventlog/models/models_event_v2.py
accelbyte_py_sdk/api/eventlog/models/models_generic_query_payload.py
accelbyte_py_sdk/api/eventlog/models/models_multiple_agent_type.py
accelbyte_py_sdk/api/eventlog/models/models_multiple_event_id.py
accelbyte_py_sdk/api/eventlog/models/models_multiple_event_level.py
accelbyte_py_sdk/api/eventlog/models/models_multiple_event_type.py
accelbyte_py_sdk/api/eventlog/models/models_multiple_ux.py
accelbyte_py_sdk/api/eventlog/models/models_pagination.py
accelbyte_py_sdk/api/eventlog/models/models_paging.py
accelbyte_py_sdk/api/eventlog/models/models_user_last_activity.py
accelbyte_py_sdk/api/eventlog/models/models_ux.py
accelbyte_py_sdk/api/eventlog/operations/__init__.py
accelbyte_py_sdk/api/eventlog/operations/event/__init__.py
accelbyte_py_sdk/api/eventlog/operations/event/get_event_by_event_id_handler.py
accelbyte_py_sdk/api/eventlog/operations/event/get_event_by_event_type_8d579c.py
accelbyte_py_sdk/api/eventlog/operations/event/get_event_by_event_type_f075bc.py
accelbyte_py_sdk/api/eventlog/operations/event/get_event_by_namespace_handler.py
accelbyte_py_sdk/api/eventlog/operations/event/get_event_by_user_event_af55e0.py
accelbyte_py_sdk/api/eventlog/operations/event/get_event_by_user_id_an_30e3ad.py
accelbyte_py_sdk/api/eventlog/operations/event/get_event_by_user_id_an_c0de1a.py
accelbyte_py_sdk/api/eventlog/operations/event/get_event_by_user_id_handler.py
accelbyte_py_sdk_service_eventlog-0.7.0.dist-info/METADATA
accelbyte_py_sdk_service_eventlog-0.7.0.dist-info/WHEEL
accelbyte_py_sdk_service_eventlog-0.7.0.dist-info/top_level.txt
accelbyte_py_sdk_service_eventlog-0.7.0.dist-info/RECORD
