Metadata-Version: 2.1
Name: accelbyte-py-sdk-service-eventlog
Version: 0.7.0
Summary: AccelByte Python SDK - AccelByte Gaming Services Event Log Service
Requires-Python: >=3.9
Requires-Dist: accelbyte-py-sdk-core
